dscribe/__init__.py
dscribe/ext.cpython-314-darwin.so
dscribe/kernels/localsimilaritykernel.py
dscribe/kernels/averagekernel.py
dscribe/kernels/__init__.py
dscribe/kernels/rematchkernel.py
dscribe/core/system.py
dscribe/core/__init__.py
dscribe/core/lattice.py
dscribe/ext/descriptorlocal.cpp
dscribe/ext/mbtr.h
dscribe/ext/descriptor.cpp
dscribe/ext/soap.cpp
dscribe/ext/geometry.cpp
dscribe/ext/celllist.cpp
dscribe/ext/coulombmatrix.h
dscribe/ext/descriptor.h
dscribe/ext/acsf.h
dscribe/ext/soapGeneral.cpp
dscribe/ext/weighting.h
dscribe/ext/soapGTO.h
dscribe/ext/ext.cpp
dscribe/ext/coulombmatrix.cpp
dscribe/ext/soapGeneral.h
dscribe/ext/soapGTO.cpp
dscribe/ext/descriptorglobal.cpp
dscribe/ext/descriptorglobal.h
dscribe/ext/weighting.cpp
dscribe/ext/soap.h
dscribe/ext/acsf.cpp
dscribe/ext/celllist.h
dscribe/ext/descriptorlocal.h
dscribe/ext/geometry.h
dscribe/ext/mbtr.cpp
dscribe/utils/species.py
dscribe/utils/__init__.py
dscribe/utils/stats.py
dscribe/utils/geometry.py
dscribe/utils/dimensionality.py
dscribe/descriptors/descriptor.py
dscribe/descriptors/descriptorglobal.py
dscribe/descriptors/descriptormatrix.py
dscribe/descriptors/soap.py
dscribe/descriptors/__init__.py
dscribe/descriptors/coulombmatrix.py
dscribe/descriptors/ewaldsummatrix.py
dscribe/descriptors/acsf.py
dscribe/descriptors/descriptorlocal.py
dscribe/descriptors/sinematrix.py
dscribe/descriptors/lmbtr.py
dscribe/descriptors/valleoganov.py
dscribe/descriptors/mbtr.py
dscribe-2.1.2.dist-info/RECORD
dscribe-2.1.2.dist-info/WHEEL
dscribe-2.1.2.dist-info/top_level.txt
dscribe-2.1.2.dist-info/METADATA
dscribe-2.1.2.dist-info/licenses/LICENSE
