Metadata-Version: 2.4
Name: dscribe
Version: 2.1.2
Summary: A Python package for creating feature transformations in applications of machine learning to materials science.
License:                                  Apache License
Project-URL: Documentation, https://singroup.github.io/dscribe/latest/
Project-URL: Source, https://singroup.github.io/dscribe
Keywords: descriptor,machine learning,atomistic structure,materials science
Classifier: Development Status :: 5 - Production/Stable
Classifier: Intended Audience :: Science/Research
Classifier: Intended Audience :: Developers
Classifier: Topic :: Scientific/Engineering
Classifier: Topic :: Scientific/Engineering :: Physics
Classifier: License :: OSI Approved :: Apache Software License
Classifier: Operating System :: MacOS
Classifier: Operating System :: Unix
Classifier: Programming Language :: C
Classifier: Programming Language :: C++
Classifier: Programming Language :: Python
Classifier: Programming Language :: Python :: 3
Classifier: Programming Language :: Python :: 3.9
Classifier: Programming Language :: Python :: 3.10
Classifier: Programming Language :: Python :: 3.11
Classifier: Programming Language :: Python :: 3.12
Classifier: Programming Language :: Python :: 3.13
Classifier: Programming Language :: Python :: 3 :: Only
Requires-Python: >=3.9
License-File: LICENSE
Requires-Dist: numpy
Requires-Dist: scipy
Requires-Dist: ase>=3.19.0
Requires-Dist: scikit-learn
Requires-Dist: joblib>=1.0.0
Requires-Dist: sparse
Provides-Extra: dev
Requires-Dist: coverage; extra == "dev"
Requires-Dist: ruff; extra == "dev"
Requires-Dist: coveralls; extra == "dev"
Requires-Dist: pymatgen>=2023.3.23; extra == "dev"
Requires-Dist: sphinx; extra == "dev"
Requires-Dist: sphinx_rtd_theme; extra == "dev"
Requires-Dist: sphinxcontrib-bibtex; extra == "dev"
Requires-Dist: pytest; extra == "dev"
Dynamic: license-file
Dynamic: requires-python
